pylitematic/__init__.py
pylitematic/block_palette.py
pylitematic/block_property.py
pylitematic/block_state.py
pylitematic/geometry.py
pylitematic/property_cache.py
pylitematic/region.py
pylitematic/resource_location.py
pylitematic/schematic.py
pylitematic/test.py
pylitematic-0.0.5.dist-info/METADATA
pylitematic-0.0.5.dist-info/WHEEL
pylitematic-0.0.5.dist-info/top_level.txt
pylitematic-0.0.5.dist-info/RECORD
