Metadata-Version: 2.4
Name: pylitematic
Version: 0.0.5
Summary: Load, modify, and save Litematica schematics
Author-email: Boscawinks <bosca.winks@gmx.de>
License: GPL-3.0-only
Project-URL: Homepage, https://github.com/boscawinks/pylitematic
Project-URL: Repository, https://github.com/boscawinks/pylitematic
Project-URL: Issues, https://github.com/boscawinks/pylitematic/issues
Classifier: Development Status :: 2 - Pre-Alpha
Classifier: Programming Language :: Python :: 3
Classifier: Operating System :: OS Independent
Classifier: Topic :: Utilities
Requires-Python: >=3.10.12
Requires-Dist: bitpacking>=0.1.0
Requires-Dist: nbtlib>=2.0.4
Requires-Dist: numpy>=2.2.6
Requires-Dist: twos>=0.0.1
Provides-Extra: dev
Requires-Dist: pytest; extra == "dev"
